mydshit/__main__.py
mydshit/configloader.py
mydshit-0.1.0.dist-info/METADATA
mydshit-0.1.0.dist-info/WHEEL
mydshit-0.1.0.dist-info/RECORD
