Metadata-Version: 2.1
Name: mydshit
Version: 0.1.0
Summary: random shit - make your distro
License: MIT
Author: alexeev-prog
Author-email: alexeev.dev@mail.ru
Requires-Python: >=3.9,<4.0
Classifier: License :: OSI Approved :: MIT License
Classifier: Programming Language :: Python :: 3
Classifier: Programming Language :: Python :: 3.9
Classifier: Programming Language :: Python :: 3.10
Classifier: Programming Language :: Python :: 3.11
Classifier: Programming Language :: Python :: 3.12
Classifier: Programming Language :: Python :: 3.13
Requires-Dist: click (>=8.1.8,<9.0.0)
Requires-Dist: loguru (>=0.7.3,<0.8.0)
Requires-Dist: orjson (>=3.10.15,<4.0.0)
Requires-Dist: pyyaml (>=6.0.2,<7.0.0)
Requires-Dist: rich (>=13.9.4,<14.0.0)
Requires-Dist: toml (>=0.10.2,<0.11.0)
